{
  "saved_at": "2026-01-23 16:18:38",
  "pi_hash": "c1be6c75f6",
  "trans_shape": [
    3,
    25,
    25
  ],
  "emit_shape": [
    25,
    25
  ],
  "policy_shape": [
    25,
    3
  ],
  "animal": "G386",
  "exp_date": "2023-11-17",
  "seed": 47,
  "validation_seed": 3693303795,
  "n_states": 25,
  "pde": 0.9512951855359395,
  "nll_model": 166.38444621995725,
  "nll_null": 3416.180680510199,
  "neural_similarity": NaN,
  "matrix_metric": "corr",
  "compare_metric": "pearson",
  "trace_first": -3039.642016491566,
  "trace_last": -542.6168030675303,
  "animal_accuracy": 0.8537735849056604
}