{
  "saved_at": "2026-01-23 15:25:07",
  "pi_hash": "370d2e897c",
  "trans_shape": [
    3,
    25,
    25
  ],
  "emit_shape": [
    25,
    25
  ],
  "policy_shape": [
    25,
    3
  ],
  "animal": "G386",
  "exp_date": "2023-11-09",
  "seed": 64,
  "validation_seed": 1270901598,
  "n_states": 25,
  "pde": 0.9435196352510802,
  "nll_model": 208.99141903332486,
  "nll_null": 3700.249103602362,
  "neural_similarity": NaN,
  "matrix_metric": "corr",
  "compare_metric": "pearson",
  "trace_first": -3458.2362410966457,
  "trace_last": -571.7188866560169,
  "animal_accuracy": 0.8304347826086956
}