{
  "saved_at": "2026-01-23 22:38:03",
  "pi_hash": "b64fedd884",
  "trans_shape": [
    3,
    25,
    25
  ],
  "emit_shape": [
    25,
    25
  ],
  "policy_shape": [
    25,
    3
  ],
  "animal": "G506",
  "exp_date": "2025-10-17",
  "seed": 82,
  "validation_seed": 2609367225,
  "n_states": 25,
  "pde": 0.938613566682184,
  "nll_model": 154.13730202971146,
  "nll_null": 2510.934317224401,
  "neural_similarity": NaN,
  "matrix_metric": "corr",
  "compare_metric": "pearson",
  "trace_first": -2231.1795890557933,
  "trace_last": -360.7984317220798,
  "animal_accuracy": 0.8397435897435898
}