{
  "saved_at": "2026-01-23 19:27:53",
  "pi_hash": "cda6c081af",
  "trans_shape": [
    3,
    25,
    25
  ],
  "emit_shape": [
    25,
    25
  ],
  "policy_shape": [
    25,
    3
  ],
  "animal": "G420",
  "exp_date": "2025-04-21",
  "seed": 85,
  "validation_seed": 2611763589,
  "n_states": 25,
  "pde": 0.9517948878727466,
  "nll_model": 152.61989915819277,
  "nll_null": 3166.0521555328337,
  "neural_similarity": NaN,
  "matrix_metric": "corr",
  "compare_metric": "pearson",
  "trace_first": -2913.400216336913,
  "trace_last": -465.3368090654774,
  "animal_accuracy": 0.7948717948717948
}