{
  "saved_at": "2026-01-23 15:04:08",
  "pi_hash": "7b55e93a4b",
  "trans_shape": [
    3,
    25,
    25
  ],
  "emit_shape": [
    25,
    25
  ],
  "policy_shape": [
    25,
    3
  ],
  "animal": "G386",
  "exp_date": "2023-11-07",
  "seed": 44,
  "validation_seed": 2292410022,
  "n_states": 25,
  "pde": 0.9558937491580419,
  "nll_model": 169.14419364747383,
  "nll_null": 3834.925671954135,
  "neural_similarity": NaN,
  "matrix_metric": "corr",
  "compare_metric": "pearson",
  "trace_first": -3372.39289067219,
  "trace_last": -566.4037760801745,
  "animal_accuracy": 0.788135593220339
}