{
  "saved_at": "2026-01-23 15:08:11",
  "pi_hash": "6fc2b85934",
  "trans_shape": [
    3,
    25,
    25
  ],
  "emit_shape": [
    25,
    25
  ],
  "policy_shape": [
    25,
    3
  ],
  "animal": "G386",
  "exp_date": "2023-11-07",
  "seed": 84,
  "validation_seed": 2292410022,
  "n_states": 25,
  "pde": 0.9552090524762532,
  "nll_model": 171.7699545299671,
  "nll_null": 3834.925671954135,
  "neural_similarity": NaN,
  "matrix_metric": "corr",
  "compare_metric": "pearson",
  "trace_first": -3543.9856702131765,
  "trace_last": -572.27713910005,
  "animal_accuracy": 0.788135593220339
}