{
  "saved_at": "2026-01-23 14:20:50",
  "pi_hash": "fd31a225a7",
  "trans_shape": [
    3,
    25,
    25
  ],
  "emit_shape": [
    25,
    25
  ],
  "policy_shape": [
    25,
    3
  ],
  "animal": "G386",
  "exp_date": "2023-11-01",
  "seed": 55,
  "validation_seed": 3352294396,
  "n_states": 25,
  "pde": 0.962176714537515,
  "nll_model": 141.51656596032248,
  "nll_null": 3741.519654623481,
  "neural_similarity": NaN,
  "matrix_metric": "corr",
  "compare_metric": "pearson",
  "trace_first": -3361.6258508103424,
  "trace_last": -562.7173297188568,
  "animal_accuracy": 0.8405172413793104
}