{
  "saved_at": "2026-01-23 13:21:29",
  "pi_hash": "87472b07e6",
  "trans_shape": [
    3,
    25,
    25
  ],
  "emit_shape": [
    25,
    25
  ],
  "policy_shape": [
    25,
    3
  ],
  "animal": "G386",
  "exp_date": "2023-10-20",
  "seed": 80,
  "validation_seed": 525043989,
  "n_states": 25,
  "pde": 0.9467147565116293,
  "nll_model": 170.8626549818215,
  "nll_null": 3206.56609215104,
  "neural_similarity": NaN,
  "matrix_metric": "corr",
  "compare_metric": "pearson",
  "trace_first": -2823.6425876340472,
  "trace_last": -482.99841801748363,
  "animal_accuracy": 0.7346938775510204
}