{
  "saved_at": "2026-01-23 22:06:15",
  "pi_hash": "28d09d0e4a",
  "trans_shape": [
    3,
    25,
    25
  ],
  "emit_shape": [
    25,
    25
  ],
  "policy_shape": [
    25,
    3
  ],
  "animal": "G402",
  "exp_date": "2023-12-11",
  "seed": 34,
  "validation_seed": 385222474,
  "n_states": 25,
  "pde": 0.9404855006054712,
  "nll_model": 194.4621184545901,
  "nll_null": 3267.4746563098374,
  "neural_similarity": NaN,
  "matrix_metric": "corr",
  "compare_metric": "pearson",
  "trace_first": -2853.710468817198,
  "trace_last": -565.5758308812814,
  "animal_accuracy": 0.7135678391959799
}