{
  "saved_at": "2026-01-23 22:06:52",
  "pi_hash": "6033f5fcf6",
  "trans_shape": [
    3,
    25,
    25
  ],
  "emit_shape": [
    25,
    25
  ],
  "policy_shape": [
    25,
    3
  ],
  "animal": "G402",
  "exp_date": "2023-12-11",
  "seed": 40,
  "validation_seed": 385222474,
  "n_states": 25,
  "pde": 0.9475171043899229,
  "nll_model": 171.48653129568174,
  "nll_null": 3267.4746563098374,
  "neural_similarity": NaN,
  "matrix_metric": "corr",
  "compare_metric": "pearson",
  "trace_first": -2897.508421489322,
  "trace_last": -498.91827325372424,
  "animal_accuracy": 0.7135678391959799
}