{
  "saved_at": "2026-01-23 14:50:57",
  "pi_hash": "616ea2cd32",
  "trans_shape": [
    3,
    25,
    25
  ],
  "emit_shape": [
    25,
    25
  ],
  "policy_shape": [
    25,
    3
  ],
  "animal": "G386",
  "exp_date": "2023-11-06",
  "seed": 1,
  "validation_seed": 1237680341,
  "n_states": 25,
  "pde": 0.9291250508837798,
  "nll_model": 222.0302952732501,
  "nll_null": 3132.704827895773,
  "neural_similarity": NaN,
  "matrix_metric": "corr",
  "compare_metric": "pearson",
  "trace_first": -2890.1764755992745,
  "trace_last": -458.76728532604466,
  "animal_accuracy": 0.7823834196891192
}