{
  "saved_at": "2026-01-23 11:14:16",
  "pi_hash": "829e03f410",
  "trans_shape": [
    3,
    25,
    25
  ],
  "emit_shape": [
    25,
    25
  ],
  "policy_shape": [
    25,
    3
  ],
  "animal": "G375",
  "exp_date": "2023-02-24",
  "seed": 68,
  "validation_seed": 2000014171,
  "n_states": 25,
  "pde": 0.9487442727606448,
  "nll_model": 186.31577205252802,
  "nll_null": 3635.0234810339603,
  "neural_similarity": NaN,
  "matrix_metric": "corr",
  "compare_metric": "pearson",
  "trace_first": -3286.0963207919967,
  "trace_last": -543.2491942341255,
  "animal_accuracy": 0.7713004484304933
}