{
  "saved_at": "2026-01-23 13:30:03",
  "pi_hash": "e5a6887f0e",
  "trans_shape": [
    3,
    25,
    25
  ],
  "emit_shape": [
    25,
    25
  ],
  "policy_shape": [
    25,
    3
  ],
  "animal": "G386",
  "exp_date": "2023-10-23",
  "seed": 66,
  "validation_seed": 3216602646,
  "n_states": 25,
  "pde": 0.9618602600143128,
  "nll_model": 138.40273141815496,
  "nll_null": 3628.83258957963,
  "neural_similarity": NaN,
  "matrix_metric": "corr",
  "compare_metric": "pearson",
  "trace_first": -3123.125939795589,
  "trace_last": -540.1327961226449,
  "animal_accuracy": 0.7342342342342343
}